sndfile/__init__.py
sndfile/_sndfile.abi3.so
sndfile/build.py
sndfile/formats.py
sndfile/io.py
sndfile-0.1.2.dist-info/METADATA
sndfile-0.1.2.dist-info/RECORD
sndfile-0.1.2.dist-info/WHEEL
sndfile-0.1.2.dist-info/top_level.txt
