Metadata-Version: 2.1
Name: sndfile
Version: 0.1.2
Summary: A CFFI wrapper around libsndfile
Home-page: https://github.com/sangoma/sndfile
Author: Simon Gomizelj
Author-email: simon@vodik.xyz
License: UNKNOWN
Platform: UNKNOWN
Classifier: Development Status :: 3 - Alpha
Classifier: Intended Audience :: Developers
Classifier: License :: OSI Approved :: GNU Lesser General Public License v3 or later (LGPLv3+)
Classifier: Operating System :: OS Independent
Classifier: Programming Language :: Python
Classifier: Programming Language :: Python :: 3.5
Classifier: Programming Language :: Python :: 3.6
Classifier: Programming Language :: Python :: Implementation :: CPython
Classifier: Programming Language :: Python :: Implementation :: PyPy
Classifier: Topic :: Utilities
Requires-Dist: cffi (>=1.0.0)
